{
  "annotations": {
    "list": [
      {
        "builtIn": 1,
        "datasource": {
          "type": "datasource",
          "uid": "grafana"
        },
        "enable": true,
        "hide": true,
        "iconColor": "rgba(0, 211, 255, 1)",
        "name": "Annotations & Alerts",
        "target": {
          "limit": 100,
          "matchAny": false,
          "tags": [],
          "type": "dashboard"
        },
        "type": "dashboard"
      }
    ]
  },
  "editable": true,
  "fiscalYearStartMonth": 0,
  "graphTooltip": 0,
  "id": 8,
  "links": [],
  "liveNow": false,
  "panels": [
    {
      "collapsed": false,
      "datasource": {
        "type": "datasource",
        "uid": "grafana"
      },
      "gridPos": {
        "h": 1,
        "w": 24,
        "x": 0,
        "y": 0
      },
      "id": 20,
      "panels": [],
      "title": "Minecraft Servers",
      "type": "row"
    },
    {
      "datasource": {
        "type": "prometheus",
        "uid": "sBp1YgX7k"
      },
      "fieldConfig": {
        "defaults": {
          "color": {
            "mode": "thresholds"
          },
          "custom": {
            "fillOpacity": 70,
            "lineWidth": 0,
            "spanNulls": false
          },
          "mappings": [],
          "thresholds": {
            "mode": "absolute",
            "steps": [
              {
                "color": "dark-red",
                "value": null
              },
              {
                "color": "green",
                "value": 1
              }
            ]
          }
        },
        "overrides": [
          {
            "matcher": {
              "id": "byFrameRefID",
              "options": "A"
            },
            "properties": [
              {
                "id": "mappings",
                "value": [
                  {
                    "options": {
                      "0": {
                        "index": 0,
                        "text": "Down"
                      },
                      "1": {
                        "index": 1,
                        "text": "Up"
                      }
                    },
                    "type": "value"
                  }
                ]
              }
            ]
          }
        ]
      },
      "gridPos": {
        "h": 9,
        "w": 4,
        "x": 0,
        "y": 1
      },
      "id": 18,
      "options": {
        "alignValue": "left",
        "legend": {
          "displayMode": "hidden",
          "placement": "bottom"
        },
        "mergeValues": true,
        "rowHeight": 0.9,
        "showValue": "never",
        "tooltip": {
          "mode": "single",
          "sort": "none"
        }
      },
      "pluginVersion": "8.1.0",
      "targets": [
        {
          "exemplar": true,
          "expr": "sum by (server_host) (minecraft_status_healthy{})",
          "format": "time_series",
          "instant": false,
          "interval": "",
          "legendFormat": "{{ server_host }}",
          "refId": "A"
        }
      ],
      "title": "Minecraft Server Status",
      "type": "state-timeline"
    },
    {
      "datasource": {
        "type": "prometheus",
        "uid": "sBp1YgX7k"
      },
      "fieldConfig": {
        "defaults": {
          "color": {
            "mode": "palette-classic"
          },
          "custom": {
            "axisLabel": "",
            "axisPlacement": "auto",
            "axisSoftMax": 0.05,
            "barAlignment": 0,
            "drawStyle": "line",
            "fillOpacity": 0,
            "gradientMode": "none",
            "hideFrom": {
              "legend": false,
              "tooltip": false,
              "viz": false
            },
            "lineInterpolation": "linear",
            "lineWidth": 1,
            "pointSize": 5,
            "scaleDistribution": {
              "log": 2,
              "type": "log"
            },
            "showPoints": "auto",
            "spanNulls": false,
            "stacking": {
              "group": "A",
              "mode": "none"
            },
            "thresholdsStyle": {
              "mode": "off"
            }
          },
          "mappings": [],
          "thresholds": {
            "mode": "absolute",
            "steps": [
              {
                "color": "green",
                "value": null
              },
              {
                "color": "red",
                "value": 80
              }
            ]
          },
          "unit": "s"
        },
        "overrides": []
      },
      "gridPos": {
        "h": 9,
        "w": 9,
        "x": 4,
        "y": 1
      },
      "id": 22,
      "options": {
        "legend": {
          "calcs": [],
          "displayMode": "hidden",
          "placement": "bottom"
        },
        "tooltip": {
          "mode": "multi",
          "sort": "none"
        }
      },
      "targets": [
        {
          "exemplar": true,
          "expr": "minecraft_status_response_time_seconds{}",
          "interval": "",
          "legendFormat": "{{ server_host }}",
          "queryType": "randomWalk",
          "refId": "A"
        }
      ],
      "title": "Server Ping",
      "type": "timeseries"
    },
    {
      "datasource": {
        "type": "prometheus",
        "uid": "sBp1YgX7k"
      },
      "fieldConfig": {
        "defaults": {
          "color": {
            "mode": "palette-classic"
          },
          "custom": {
            "axisLabel": "",
            "axisPlacement": "auto",
            "barAlignment": 0,
            "drawStyle": "line",
            "fillOpacity": 0,
            "gradientMode": "none",
            "hideFrom": {
              "legend": false,
              "tooltip": false,
              "viz": false
            },
            "lineInterpolation": "linear",
            "lineWidth": 1,
            "pointSize": 5,
            "scaleDistribution": {
              "type": "linear"
            },
            "showPoints": "auto",
            "spanNulls": false,
            "stacking": {
              "group": "A",
              "mode": "none"
            },
            "thresholdsStyle": {
              "mode": "off"
            }
          },
          "decimals": 0,
          "mappings": [],
          "max": 20,
          "min": 0,
          "thresholds": {
            "mode": "absolute",
            "steps": [
              {
                "color": "green",
                "value": null
              },
              {
                "color": "red",
                "value": 80
              }
            ]
          }
        },
        "overrides": []
      },
      "gridPos": {
        "h": 9,
        "w": 11,
        "x": 13,
        "y": 1
      },
      "id": 24,
      "options": {
        "legend": {
          "calcs": [],
          "displayMode": "hidden",
          "placement": "bottom"
        },
        "tooltip": {
          "mode": "single",
          "sort": "none"
        }
      },
      "targets": [
        {
          "exemplar": true,
          "expr": "minecraft_status_players_online_count{}",
          "interval": "",
          "legendFormat": "{{ server_host }}",
          "queryType": "randomWalk",
          "refId": "A"
        }
      ],
      "title": "Players Online",
      "type": "timeseries"
    },
    {
      "collapsed": false,
      "datasource": {
        "type": "datasource",
        "uid": "grafana"
      },
      "gridPos": {
        "h": 1,
        "w": 24,
        "x": 0,
        "y": 10
      },
      "id": 26,
      "panels": [],
      "title": "Traefik",
      "type": "row"
    },
    {
      "datasource": {
        "type": "prometheus",
        "uid": "sBp1YgX7k"
      },
      "description": "",
      "fieldConfig": {
        "defaults": {
          "color": {
            "mode": "palette-classic"
          },
          "custom": {
            "axisLabel": "",
            "axisPlacement": "auto",
            "barAlignment": 0,
            "drawStyle": "line",
            "fillOpacity": 0,
            "gradientMode": "none",
            "hideFrom": {
              "legend": false,
              "tooltip": false,
              "viz": false
            },
            "lineInterpolation": "linear",
            "lineWidth": 1,
            "pointSize": 5,
            "scaleDistribution": {
              "type": "linear"
            },
            "showPoints": "auto",
            "spanNulls": false,
            "stacking": {
              "group": "A",
              "mode": "none"
            },
            "thresholdsStyle": {
              "mode": "off"
            }
          },
          "mappings": [],
          "thresholds": {
            "mode": "absolute",
            "steps": [
              {
                "color": "green",
                "value": null
              },
              {
                "color": "red",
                "value": 80
              }
            ]
          }
        },
        "overrides": []
      },
      "gridPos": {
        "h": 8,
        "w": 12,
        "x": 0,
        "y": 11
      },
      "id": 28,
      "options": {
        "legend": {
          "calcs": [],
          "displayMode": "list",
          "placement": "bottom"
        },
        "tooltip": {
          "mode": "single",
          "sort": "none"
        }
      },
      "targets": [
        {
          "exemplar": true,
          "expr": "sum by (service) (traefik_service_open_connections{})",
          "interval": "",
          "legendFormat": "{{ service }}",
          "queryType": "randomWalk",
          "refId": "A"
        }
      ],
      "title": "Open Connections",
      "type": "timeseries"
    },
    {
      "datasource": {
        "type": "prometheus",
        "uid": "sBp1YgX7k"
      },
      "fieldConfig": {
        "defaults": {
          "color": {
            "mode": "palette-classic"
          },
          "custom": {
            "axisLabel": "",
            "axisPlacement": "auto",
            "barAlignment": 0,
            "drawStyle": "line",
            "fillOpacity": 0,
            "gradientMode": "none",
            "hideFrom": {
              "legend": false,
              "tooltip": false,
              "viz": false
            },
            "lineInterpolation": "linear",
            "lineWidth": 1,
            "pointSize": 5,
            "scaleDistribution": {
              "type": "linear"
            },
            "showPoints": "auto",
            "spanNulls": false,
            "stacking": {
              "group": "A",
              "mode": "none"
            },
            "thresholdsStyle": {
              "mode": "off"
            }
          },
          "mappings": [],
          "thresholds": {
            "mode": "absolute",
            "steps": [
              {
                "color": "green",
                "value": null
              },
              {
                "color": "red",
                "value": 80
              }
            ]
          }
        },
        "overrides": []
      },
      "gridPos": {
        "h": 8,
        "w": 12,
        "x": 12,
        "y": 11
      },
      "id": 30,
      "options": {
        "legend": {
          "calcs": [],
          "displayMode": "list",
          "placement": "bottom"
        },
        "tooltip": {
          "mode": "single",
          "sort": "none"
        }
      },
      "pluginVersion": "8.1.0",
      "targets": [
        {
          "exemplar": true,
          "expr": "sum by (service) (rate(traefik_service_requests_total{}[1m]))",
          "interval": "",
          "legendFormat": "{{ service }}",
          "queryType": "randomWalk",
          "refId": "A"
        }
      ],
      "title": "Requests in last minute",
      "type": "timeseries"
    },
    {
      "collapsed": false,
      "datasource": {
        "type": "datasource",
        "uid": "grafana"
      },
      "gridPos": {
        "h": 1,
        "w": 24,
        "x": 0,
        "y": 19
      },
      "id": 47,
      "panels": [],
      "title": "Deluge",
      "type": "row"
    },
    {
      "datasource": {
        "type": "prometheus",
        "uid": "sBp1YgX7k"
      },
      "fieldConfig": {
        "defaults": {
          "color": {
            "mode": "thresholds"
          },
          "mappings": [],
          "thresholds": {
            "mode": "absolute",
            "steps": [
              {
                "color": "green",
                "value": null
              }
            ]
          }
        },
        "overrides": []
      },
      "gridPos": {
        "h": 8,
        "w": 2,
        "x": 0,
        "y": 20
      },
      "id": 59,
      "options": {
        "colorMode": "value",
        "graphMode": "none",
        "justifyMode": "auto",
        "orientation": "horizontal",
        "reduceOptions": {
          "calcs": [
            "lastNotNull"
          ],
          "fields": "",
          "values": false
        },
        "text": {},
        "textMode": "value_and_name"
      },
      "pluginVersion": "8.5.2",
      "targets": [
        {
          "exemplar": true,
          "expr": "sum by (tracker) (deluge_torrents{job=\"deluge\", tracker=~\"ggn|mam|emp|pub\"})",
          "interval": "",
          "legendFormat": "{{ tracker }}",
          "queryType": "randomWalk",
          "refId": "A"
        }
      ],
      "title": "Torrents",
      "type": "stat"
    },
    {
      "aliasColors": {},
      "bars": false,
      "dashLength": 10,
      "dashes": false,
      "datasource": {
        "type": "prometheus",
        "uid": "sBp1YgX7k"
      },
      "fieldConfig": {
        "defaults": {
          "unit": "decbytes"
        },
        "overrides": []
      },
      "fill": 1,
      "fillGradient": 0,
      "gridPos": {
        "h": 8,
        "w": 11,
        "x": 2,
        "y": 20
      },
      "hiddenSeries": false,
      "id": 61,
      "legend": {
        "avg": false,
        "current": false,
        "max": false,
        "min": false,
        "show": false,
        "total": false,
        "values": false
      },
      "lines": true,
      "linewidth": 1,
      "nullPointMode": "null",
      "options": {
        "alertThreshold": true
      },
      "percentage": false,
      "pluginVersion": "8.5.2",
      "pointradius": 2,
      "points": false,
      "renderer": "flot",
      "seriesOverrides": [
        {
          "$$hashKey": "object:18",
          "alias": "/download/",
          "transform": "negative-Y"
        }
      ],
      "spaceLength": 10,
      "stack": false,
      "steppedLine": false,
      "targets": [
        {
          "exemplar": true,
          "expr": "sum by (tracker) (rate(deluge_libtorrent_net_recv_bytes_total{tracker=~\"ggn|mam|emp|pub\"}[24h]))",
          "interval": "",
          "legendFormat": "{{ tracker }} download",
          "queryType": "randomWalk",
          "refId": "A"
        },
        {
          "exemplar": true,
          "expr": "sum by (tracker) (rate(deluge_libtorrent_net_sent_bytes_total{tracker=~\"ggn|mam|emp|pub\"}[24h]))",
          "hide": false,
          "interval": "",
          "legendFormat": "{{ tracker }} upload",
          "refId": "B"
        }
      ],
      "thresholds": [],
      "timeRegions": [],
      "title": "Traffic",
      "tooltip": {
        "shared": true,
        "sort": 0,
        "value_type": "individual"
      },
      "type": "graph",
      "xaxis": {
        "mode": "time",
        "show": true,
        "values": []
      },
      "yaxes": [
        {
          "format": "decbytes",
          "logBase": 1,
          "show": true
        },
        {
          "format": "short",
          "logBase": 1,
          "show": true
        }
      ],
      "yaxis": {
        "align": false
      }
    },
    {
      "datasource": {
        "type": "prometheus",
        "uid": "sBp1YgX7k"
      },
      "fieldConfig": {
        "defaults": {
          "color": {
            "mode": "thresholds"
          },
          "custom": {
            "align": "left",
            "displayMode": "auto",
            "inspect": false
          },
          "mappings": [],
          "thresholds": {
            "mode": "absolute",
            "steps": [
              {
                "color": "green",
                "value": null
              }
            ]
          }
        },
        "overrides": []
      },
      "gridPos": {
        "h": 8,
        "w": 11,
        "x": 13,
        "y": 20
      },
      "id": 63,
      "options": {
        "footer": {
          "fields": "",
          "reducer": [
            "sum"
          ],
          "show": false
        },
        "frameIndex": 0,
        "showHeader": true
      },
      "pluginVersion": "8.5.2",
      "targets": [
        {
          "exemplar": true,
          "expr": "deluge_libtorrent_ses_num_seeding_torrents{}",
          "hide": false,
          "instant": false,
          "interval": "",
          "legendFormat": "{{tracker}} seeding",
          "refId": "A"
        },
        {
          "exemplar": true,
          "expr": "deluge_libtorrent_ses_num_checking_torrents{} ",
          "hide": false,
          "interval": "",
          "legendFormat": "{{tracker}} checking",
          "refId": "B"
        },
        {
          "exemplar": true,
          "expr": "deluge_libtorrent_ses_num_downloading_torrents{}",
          "hide": false,
          "interval": "",
          "legendFormat": "{{tracker}} downloading",
          "refId": "C"
        },
        {
          "exemplar": true,
          "expr": "deluge_libtorrent_ses_num_error_torrents{}",
          "hide": false,
          "interval": "",
          "legendFormat": "{{tracker}} error",
          "refId": "D"
        },
        {
          "exemplar": true,
          "expr": "deluge_libtorrent_ses_num_stopped_torrents{}",
          "hide": false,
          "interval": "",
          "legendFormat": "{{tracker}} stopped",
          "refId": "E"
        }
      ],
      "title": "Torrent States",
      "transformations": [
        {
          "id": "reduce",
          "options": {
            "includeTimeField": false,
            "mode": "seriesToRows",
            "reducers": [
              "lastNotNull"
            ]
          }
        }
      ],
      "type": "table"
    },
    {
      "collapsed": false,
      "datasource": {
        "type": "datasource",
        "uid": "grafana"
      },
      "gridPos": {
        "h": 1,
        "w": 24,
        "x": 0,
        "y": 28
      },
      "id": 49,
      "panels": [],
      "title": "Plex",
      "type": "row"
    },
    {
      "datasource": {
        "type": "prometheus",
        "uid": "sBp1YgX7k"
      },
      "fieldConfig": {
        "defaults": {
          "color": {
            "mode": "thresholds"
          },
          "mappings": [],
          "thresholds": {
            "mode": "absolute",
            "steps": [
              {
                "color": "green",
                "value": null
              }
            ]
          }
        },
        "overrides": []
      },
      "gridPos": {
        "h": 5,
        "w": 6,
        "x": 0,
        "y": 29
      },
      "id": 65,
      "options": {
        "colorMode": "none",
        "graphMode": "none",
        "justifyMode": "auto",
        "orientation": "auto",
        "reduceOptions": {
          "calcs": [
            "lastNotNull"
          ],
          "fields": "",
          "values": false
        },
        "text": {},
        "textMode": "auto"
      },
      "pluginVersion": "8.5.2",
      "targets": [
        {
          "exemplar": true,
          "expr": "plex_library_section_size_count{name=\"Movies\"}",
          "interval": "",
          "legendFormat": "Movies",
          "queryType": "randomWalk",
          "refId": "A"
        },
        {
          "exemplar": true,
          "expr": "plex_library_section_size_count{name=\"Shows\"}",
          "hide": false,
          "interval": "",
          "legendFormat": "TV Shows",
          "refId": "B"
        },
        {
          "exemplar": true,
          "expr": "plex_library_section_size_count{name=\"Music\"}",
          "hide": false,
          "interval": "",
          "legendFormat": "Music Artists",
          "refId": "C"
        }
      ],
      "title": "Library Size",
      "type": "stat"
    },
    {
      "datasource": {
        "type": "prometheus",
        "uid": "sBp1YgX7k"
      },
      "fieldConfig": {
        "defaults": {
          "color": {
            "mode": "thresholds"
          },
          "mappings": [],
          "thresholds": {
            "mode": "absolute",
            "steps": [
              {
                "color": "green",
                "value": null
              },
              {
                "color": "red",
                "value": 80
              }
            ]
          }
        },
        "overrides": []
      },
      "gridPos": {
        "h": 5,
        "w": 5,
        "x": 6,
        "y": 29
      },
      "id": 67,
      "options": {
        "colorMode": "value",
        "graphMode": "area",
        "justifyMode": "auto",
        "orientation": "auto",
        "reduceOptions": {
          "calcs": [
            "lastNotNull"
          ],
          "fields": "",
          "values": false
        },
        "text": {},
        "textMode": "auto"
      },
      "pluginVersion": "8.5.2",
      "targets": [
        {
          "exemplar": true,
          "expr": "plex_sessions_active_count{}",
          "interval": "",
          "legendFormat": "",
          "queryType": "randomWalk",
          "refId": "A"
        }
      ],
      "title": "Current Sessions",
      "type": "stat"
    },
    {
      "datasource": {
        "type": "prometheus",
        "uid": "sBp1YgX7k"
      },
      "fieldConfig": {
        "defaults": {
          "color": {
            "mode": "thresholds"
          },
          "mappings": [],
          "thresholds": {
            "mode": "absolute",
            "steps": [
              {
                "color": "green",
                "value": null
              },
              {
                "color": "red",
                "value": 80
              }
            ]
          }
        },
        "overrides": []
      },
      "gridPos": {
        "h": 5,
        "w": 3,
        "x": 11,
        "y": 29
      },
      "id": 69,
      "options": {
        "colorMode": "none",
        "graphMode": "none",
        "justifyMode": "auto",
        "orientation": "auto",
        "reduceOptions": {
          "calcs": [
            "lastNotNull"
          ],
          "fields": "",
          "values": false
        },
        "text": {},
        "textMode": "auto"
      },
      "pluginVersion": "8.5.2",
      "targets": [
        {
          "exemplar": true,
          "expr": "max_over_time(plex_sessions_active_count[24h])",
          "interval": "",
          "legendFormat": "Last Day",
          "queryType": "randomWalk",
          "refId": "A"
        },
        {
          "exemplar": true,
          "expr": "max_over_time(plex_sessions_active_count[7d])",
          "hide": false,
          "interval": "",
          "legendFormat": "Last Week",
          "refId": "B"
        },
        {
          "exemplar": true,
          "expr": "max_over_time(plex_sessions_active_count[30d])",
          "hide": false,
          "interval": "",
          "legendFormat": "Last Month",
          "refId": "C"
        }
      ],
      "title": "Peak Sessions",
      "type": "stat"
    },
    {
      "collapsed": false,
      "datasource": {
        "type": "datasource",
        "uid": "grafana"
      },
      "gridPos": {
        "h": 1,
        "w": 24,
        "x": 0,
        "y": 34
      },
      "id": 55,
      "panels": [],
      "title": "SabNZBD",
      "type": "row"
    },
    {
      "datasource": {
        "type": "prometheus",
        "uid": "sBp1YgX7k"
      },
      "fieldConfig": {
        "defaults": {
          "color": {
            "mode": "palette-classic"
          },
          "custom": {
            "axisLabel": "",
            "axisPlacement": "auto",
            "barAlignment": 0,
            "drawStyle": "line",
            "fillOpacity": 0,
            "gradientMode": "none",
            "hideFrom": {
              "legend": false,
              "tooltip": false,
              "viz": false
            },
            "lineInterpolation": "linear",
            "lineWidth": 1,
            "pointSize": 5,
            "scaleDistribution": {
              "type": "linear"
            },
            "showPoints": "auto",
            "spanNulls": false,
            "stacking": {
              "group": "A",
              "mode": "none"
            },
            "thresholdsStyle": {
              "mode": "off"
            }
          },
          "mappings": [],
          "thresholds": {
            "mode": "absolute",
            "steps": [
              {
                "color": "green"
              },
              {
                "color": "red",
                "value": 80
              }
            ]
          },
          "unit": "bytes"
        },
        "overrides": []
      },
      "gridPos": {
        "h": 8,
        "w": 12,
        "x": 0,
        "y": 35
      },
      "id": 73,
      "options": {
        "legend": {
          "calcs": [],
          "displayMode": "hidden",
          "placement": "bottom"
        },
        "tooltip": {
          "mode": "single",
          "sort": "none"
        }
      },
      "targets": [
        {
          "exemplar": true,
          "expr": "sabnzbd_queue_download_rate_bytes_per_second{}",
          "interval": "",
          "legendFormat": "",
          "queryType": "randomWalk",
          "refId": "A"
        }
      ],
      "title": "Download Rate",
      "type": "timeseries"
    },
    {
      "datasource": {
        "type": "prometheus",
        "uid": "sBp1YgX7k"
      },
      "fieldConfig": {
        "defaults": {
          "color": {
            "mode": "thresholds"
          },
          "mappings": [],
          "thresholds": {
            "mode": "absolute",
            "steps": [
              {
                "color": "green"
              }
            ]
          },
          "unit": "bytes"
        },
        "overrides": []
      },
      "gridPos": {
        "h": 8,
        "w": 12,
        "x": 12,
        "y": 35
      },
      "id": 71,
      "options": {
        "colorMode": "value",
        "graphMode": "none",
        "justifyMode": "auto",
        "orientation": "auto",
        "reduceOptions": {
          "calcs": [
            "lastNotNull"
          ],
          "fields": "",
          "values": false
        },
        "text": {},
        "textMode": "auto"
      },
      "pluginVersion": "8.5.2",
      "targets": [
        {
          "exemplar": true,
          "expr": "sabnzbd_download_bytes{}",
          "interval": "",
          "legendFormat": "{{ period }}",
          "queryType": "randomWalk",
          "refId": "A"
        }
      ],
      "title": "Total Download",
      "type": "stat"
    },
    {
      "datasource": {
        "type": "prometheus",
        "uid": "sBp1YgX7k"
      },
      "fieldConfig": {
        "defaults": {
          "color": {
            "mode": "palette-classic"
          },
          "custom": {
            "axisLabel": "",
            "axisPlacement": "auto",
            "barAlignment": 0,
            "drawStyle": "line",
            "fillOpacity": 0,
            "gradientMode": "none",
            "hideFrom": {
              "legend": false,
              "tooltip": false,
              "viz": false
            },
            "lineInterpolation": "linear",
            "lineWidth": 1,
            "pointSize": 5,
            "scaleDistribution": {
              "type": "linear"
            },
            "showPoints": "auto",
            "spanNulls": false,
            "stacking": {
              "group": "A",
              "mode": "none"
            },
            "thresholdsStyle": {
              "mode": "off"
            }
          },
          "decimals": 0,
          "mappings": [],
          "thresholds": {
            "mode": "absolute",
            "steps": [
              {
                "color": "green"
              },
              {
                "color": "red",
                "value": 80
              }
            ]
          }
        },
        "overrides": []
      },
      "gridPos": {
        "h": 8,
        "w": 12,
        "x": 0,
        "y": 43
      },
      "id": 75,
      "options": {
        "legend": {
          "calcs": [],
          "displayMode": "hidden",
          "placement": "bottom"
        },
        "tooltip": {
          "mode": "single",
          "sort": "none"
        }
      },
      "targets": [
        {
          "exemplar": true,
          "expr": "sabnzbd_queue_size{}",
          "interval": "",
          "legendFormat": "",
          "queryType": "randomWalk",
          "refId": "A"
        }
      ],
      "title": "Items in Queue",
      "type": "timeseries"
    },
    {
      "datasource": {
        "type": "prometheus",
        "uid": "sBp1YgX7k"
      },
      "fieldConfig": {
        "defaults": {
          "color": {
            "mode": "palette-classic"
          },
          "custom": {
            "axisLabel": "",
            "axisPlacement": "auto",
            "barAlignment": 0,
            "drawStyle": "line",
            "fillOpacity": 0,
            "gradientMode": "none",
            "hideFrom": {
              "legend": false,
              "tooltip": false,
              "viz": false
            },
            "lineInterpolation": "linear",
            "lineWidth": 1,
            "pointSize": 5,
            "scaleDistribution": {
              "type": "linear"
            },
            "showPoints": "auto",
            "spanNulls": false,
            "stacking": {
              "group": "A",
              "mode": "none"
            },
            "thresholdsStyle": {
              "mode": "off"
            }
          },
          "mappings": [],
          "thresholds": {
            "mode": "absolute",
            "steps": [
              {
                "color": "green"
              },
              {
                "color": "red",
                "value": 80
              }
            ]
          },
          "unit": "bytes"
        },
        "overrides": []
      },
      "gridPos": {
        "h": 8,
        "w": 12,
        "x": 12,
        "y": 43
      },
      "id": 77,
      "options": {
        "legend": {
          "calcs": [],
          "displayMode": "hidden",
          "placement": "bottom"
        },
        "tooltip": {
          "mode": "single",
          "sort": "none"
        }
      },
      "targets": [
        {
          "exemplar": true,
          "expr": "sabnzbd_queue_total_size_bytes{}",
          "interval": "",
          "legendFormat": "",
          "queryType": "randomWalk",
          "refId": "A"
        }
      ],
      "title": "Queue Size",
      "type": "timeseries"
    },
    {
      "collapsed": false,
      "datasource": {
        "type": "datasource",
        "uid": "grafana"
      },
      "gridPos": {
        "h": 1,
        "w": 24,
        "x": 0,
        "y": 51
      },
      "id": 34,
      "panels": [],
      "title": "Uptime-Kuma",
      "type": "row"
    },
    {
      "datasource": {
        "type": "prometheus",
        "uid": "sBp1YgX7k"
      },
      "fieldConfig": {
        "defaults": {
          "color": {
            "mode": "thresholds"
          },
          "custom": {
            "fillOpacity": 70,
            "lineWidth": 0,
            "spanNulls": false
          },
          "mappings": [],
          "thresholds": {
            "mode": "absolute",
            "steps": [
              {
                "color": "green"
              },
              {
                "color": "red",
                "value": 80
              }
            ]
          }
        },
        "overrides": []
      },
      "gridPos": {
        "h": 9,
        "w": 3,
        "x": 0,
        "y": 52
      },
      "id": 39,
      "options": {
        "alignValue": "left",
        "legend": {
          "displayMode": "list",
          "placement": "bottom"
        },
        "mergeValues": true,
        "rowHeight": 0.9,
        "showValue": "never",
        "tooltip": {
          "mode": "single",
          "sort": "none"
        }
      },
      "pluginVersion": "8.1.0",
      "targets": [
        {
          "exemplar": true,
          "expr": "sum by (monitor_name) (monitor_status{})",
          "instant": false,
          "interval": "",
          "legendFormat": "{{ monitor_name }}",
          "refId": "A"
        }
      ],
      "title": "Server Status",
      "type": "state-timeline"
    },
    {
      "datasource": {
        "type": "prometheus",
        "uid": "sBp1YgX7k"
      },
      "fieldConfig": {
        "defaults": {
          "color": {
            "mode": "thresholds"
          },
          "mappings": [],
          "max": 90,
          "min": 0,
          "thresholds": {
            "mode": "absolute",
            "steps": [
              {
                "color": "dark-red"
              },
              {
                "color": "green",
                "value": 14
              }
            ]
          },
          "unit": "d"
        },
        "overrides": []
      },
      "gridPos": {
        "h": 9,
        "w": 10,
        "x": 3,
        "y": 52
      },
      "id": 32,
      "options": {
        "displayMode": "lcd",
        "minVizHeight": 10,
        "minVizWidth": 0,
        "orientation": "horizontal",
        "reduceOptions": {
          "calcs": [
            "lastNotNull"
          ],
          "fields": "",
          "values": false
        },
        "showUnfilled": true,
        "text": {}
      },
      "pluginVersion": "8.5.2",
      "targets": [
        {
          "exemplar": true,
          "expr": "monitor_cert_days_remaining{}",
          "interval": "",
          "legendFormat": "{{ monitor_name }}",
          "queryType": "randomWalk",
          "refId": "A"
        }
      ],
      "title": "Time until Cert Expiry",
      "type": "bargauge"
    },
    {
      "datasource": {
        "type": "prometheus",
        "uid": "sBp1YgX7k"
      },
      "fieldConfig": {
        "defaults": {
          "color": {
            "mode": "palette-classic"
          },
          "custom": {
            "axisLabel": "",
            "axisPlacement": "auto",
            "barAlignment": 0,
            "drawStyle": "line",
            "fillOpacity": 0,
            "gradientMode": "none",
            "hideFrom": {
              "legend": false,
              "tooltip": false,
              "viz": false
            },
            "lineInterpolation": "linear",
            "lineWidth": 1,
            "pointSize": 5,
            "scaleDistribution": {
              "log": 2,
              "type": "log"
            },
            "showPoints": "auto",
            "spanNulls": false,
            "stacking": {
              "group": "A",
              "mode": "none"
            },
            "thresholdsStyle": {
              "mode": "off"
            }
          },
          "mappings": [],
          "thresholds": {
            "mode": "absolute",
            "steps": [
              {
                "color": "green"
              },
              {
                "color": "red",
                "value": 80
              }
            ]
          },
          "unit": "ms"
        },
        "overrides": []
      },
      "gridPos": {
        "h": 9,
        "w": 11,
        "x": 13,
        "y": 52
      },
      "id": 36,
      "options": {
        "legend": {
          "calcs": [],
          "displayMode": "list",
          "placement": "bottom"
        },
        "tooltip": {
          "mode": "single",
          "sort": "none"
        }
      },
      "targets": [
        {
          "exemplar": true,
          "expr": "monitor_response_time{}",
          "interval": "",
          "legendFormat": "{{ monitor_name }}",
          "queryType": "randomWalk",
          "refId": "A"
        }
      ],
      "title": "Ping",
      "type": "timeseries"
    },
    {
      "collapsed": false,
      "datasource": {
        "type": "datasource",
        "uid": "grafana"
      },
      "gridPos": {
        "h": 1,
        "w": 24,
        "x": 0,
        "y": 61
      },
      "id": 41,
      "panels": [],
      "title": "PiHole",
      "type": "row"
    },
    {
      "datasource": {
        "type": "prometheus",
        "uid": "sBp1YgX7k"
      },
      "description": "Each point is a counter for the last 24 hours.",
      "fieldConfig": {
        "defaults": {
          "color": {
            "mode": "palette-classic"
          },
          "custom": {
            "hideFrom": {
              "legend": false,
              "tooltip": false,
              "viz": false
            }
          },
          "mappings": []
        },
        "overrides": []
      },
      "gridPos": {
        "h": 9,
        "w": 3,
        "x": 0,
        "y": 62
      },
      "id": 8,
      "options": {
        "legend": {
          "displayMode": "list",
          "placement": "bottom"
        },
        "pieType": "pie",
        "reduceOptions": {
          "calcs": [
            "lastNotNull"
          ],
          "fields": "",
          "values": false
        },
        "tooltip": {
          "mode": "single",
          "sort": "none"
        }
      },
      "pluginVersion": "8.1.0",
      "targets": [
        {
          "expr": "pihole_queries_cached",
          "interval": "",
          "legendFormat": "Cached",
          "refId": "B"
        },
        {
          "expr": "pihole_queries_forwarded",
          "interval": "",
          "legendFormat": "Forwarded",
          "refId": "C"
        },
        {
          "expr": "pihole_ads_blocked_today",
          "interval": "",
          "legendFormat": "Blocked",
          "refId": "D"
        }
      ],
      "title": "DNS Queries",
      "type": "piechart"
    },
    {
      "datasource": {
        "type": "prometheus",
        "uid": "sBp1YgX7k"
      },
      "fieldConfig": {
        "defaults": {
          "color": {
            "mode": "thresholds"
          },
          "mappings": [],
          "thresholds": {
            "mode": "absolute",
            "steps": [
              {
                "color": "green"
              },
              {
                "color": "red",
                "value": 80
              }
            ]
          }
        },
        "overrides": []
      },
      "gridPos": {
        "h": 9,
        "w": 4,
        "x": 3,
        "y": 62
      },
      "id": 43,
      "options": {
        "colorMode": "none",
        "graphMode": "none",
        "justifyMode": "auto",
        "orientation": "horizontal",
        "reduceOptions": {
          "calcs": [
            "lastNotNull"
          ],
          "fields": "",
          "values": false
        },
        "text": {},
        "textMode": "auto"
      },
      "pluginVersion": "8.5.2",
      "targets": [
        {
          "exemplar": true,
          "expr": "pihole_unique_clients{}",
          "interval": "",
          "legendFormat": "",
          "queryType": "randomWalk",
          "refId": "A"
        }
      ],
      "title": "Unique Clients",
      "type": "stat"
    }
  ],
  "refresh": "5s",
  "schemaVersion": 36,
  "style": "dark",
  "tags": [],
  "templating": {
    "list": []
  },
  "time": {
    "from": "now-6h",
    "to": "now"
  },
  "timepicker": {},
  "timezone": "",
  "title": "Services",
  "uid": "YHUzAE07z",
  "version": 2,
  "weekStart": ""
}